{
  "version": "7",
  "dialect": "postgresql",
  "entries": [
    {
      "idx": 0,
      "version": "7",
      "when": 1779317717703,
      "tag": "0000_glorious_rocket_raccoon",
      "breakpoints": true
    },
    {
      "idx": 1,
      "version": "7",
      "when": 1779322336681,
      "tag": "0001_productive_yellowjacket",
      "breakpoints": true
    },
    {
      "idx": 2,
      "version": "7",
      "when": 1779323236721,
      "tag": "0002_snake_case_columns",
      "breakpoints": true
    },
    {
      "idx": 3,
      "version": "7",
      "when": 1779750598391,
      "tag": "0003_tranquil_impossible_man",
      "breakpoints": true
    }
  ]
}